{
  "generatedAtUtc": "2026-07-19T02:33:45.4888175Z",
  "featuredFeedId": "csharp-repos",
  "totalItemCount": 12,
  "feeds": [
    {
      "id": "csharp-repos",
      "title": "Trending C# Repositories",
      "description": "Fresh .NET and C# projects gaining attention this week.",
      "itemType": "repository",
      "actionLabel": "View Repository",
      "sourceQuery": "language:C# stars:>20 pushed:>2026-07-12 archived:false",
      "items": [
        {
          "title": "v2rayN",
          "subtitle": "@2dust",
          "summary": "A GUI client for Windows, Linux and macOS, support Xray and sing-box and others v2rayN A GUI client for Windows, Linux and macOS.",
          "url": "https://github.com/2dust/v2rayN",
          "category": "C#",
          "metric": "111,702 stars",
          "publishedAtUtc": "2026-07-19T02:20:27.0000000Z"
        },
        {
          "title": "PowerShell",
          "subtitle": "@PowerShell",
          "summary": "PowerShell for every system! ![logo][] PowerShell Welcome to the PowerShell GitHub Community!",
          "url": "https://github.com/PowerShell/PowerShell",
          "category": "C#",
          "metric": "54,423 stars",
          "publishedAtUtc": "2026-07-19T01:50:08.0000000Z"
        },
        {
          "title": "jellyfin",
          "subtitle": "@jellyfin",
          "summary": "The Free Software Media System - Server Backend & API Jellyfin The Free Software Media System -- -- Jellyfin is a Free Software Media System that puts you in control of managing...",
          "url": "https://github.com/jellyfin/jellyfin",
          "category": "C#",
          "metric": "54,417 stars",
          "publishedAtUtc": "2026-07-19T02:10:29.0000000Z"
        },
        {
          "title": "Files",
          "subtitle": "@files-community",
          "summary": "A modern file manager that helps users organize their files and folders. Our mission with Files is to build the best file manager for Windows, and we’re proud to be building it...",
          "url": "https://github.com/files-community/Files",
          "category": "C#",
          "metric": "44,350 stars",
          "publishedAtUtc": "2026-07-19T02:26:16.0000000Z"
        },
        {
          "title": "ShareX",
          "subtitle": "@ShareX",
          "summary": "ShareX is a free and open-source application that enables users to capture or record any area of their screen with a... Screen capture, file sharing and productivity tool For...",
          "url": "https://github.com/ShareX/ShareX",
          "category": "C#",
          "metric": "38,704 stars",
          "publishedAtUtc": "2026-07-19T00:39:02.0000000Z"
        },
        {
          "title": "aspnetcore",
          "subtitle": "@dotnet",
          "summary": "ASP.NET Core is a cross-platform .NET framework for building modern cloud-based web applications on Windows, Mac, or... ASP.NET Core ============ ASP.NET Core is an open-source...",
          "url": "https://github.com/dotnet/aspnetcore",
          "category": "C#",
          "metric": "38,214 stars",
          "publishedAtUtc": "2026-07-18T22:47:07.0000000Z"
        }
      ]
    },
    {
      "id": "ai-tools",
      "title": "AI Tools",
      "description": "Active AI tooling repositories worth monitoring across the ecosystem.",
      "itemType": "repository",
      "actionLabel": "Explore Tool",
      "sourceQuery": "topic:ai stars:>150 archived:false",
      "items": [
        {
          "title": "Trading-Bot",
          "subtitle": "@MIgHTy-alIeN",
          "summary": "An arbitrage bot is a smart contract connected to an external automation script that controls its operation. Arbitrage Bot with Built-in Python Automation An arbitrage bot is a...",
          "url": "https://github.com/MIgHTy-alIeN/Trading-Bot",
          "category": "Solidity",
          "metric": "300 stars",
          "publishedAtUtc": "2026-07-19T02:33:04.0000000Z"
        },
        {
          "title": "electerm",
          "subtitle": "@electerm",
          "summary": "\uD83D\uDCFBTerminal/ssh/sftp/ftp/telnet/serialport/RDP/VNC/Spice client(Linux, Mac, Windows, Android) Open-sourced terminal/ssh/sftp/telnet/serialport/RDP/VNC/Spice/ftp client(linux, mac...",
          "url": "https://github.com/electerm/electerm",
          "category": "JavaScript",
          "metric": "14,516 stars",
          "publishedAtUtc": "2026-07-19T02:32:56.0000000Z"
        },
        {
          "title": "openclaw",
          "subtitle": "@openclaw",
          "summary": "Your own personal AI assistant. Any OS. Any Platform. The lobster way. \uD83E\uDD9E \uD83E\uDD9E OpenClaw — Personal AI Assistant OpenClaw is a _personal AI assistant_ you run on your own devices.",
          "url": "https://github.com/openclaw/openclaw",
          "category": "TypeScript",
          "metric": "383,411 stars",
          "publishedAtUtc": "2026-07-19T02:33:45.0000000Z"
        },
        {
          "title": "clawsweeper",
          "subtitle": "@openclaw",
          "summary": "ClawSweeper scans all issues and PRs and suggest what we can close, and why. It runs every PR / Issue once a week. \uD83E\uDD9E\uD83E\uDDF9 ClawSweeper ClawSweeper is the conservative maintenance...",
          "url": "https://github.com/openclaw/clawsweeper",
          "category": "TypeScript",
          "metric": "1,933 stars",
          "publishedAtUtc": "2026-07-19T02:32:30.0000000Z"
        },
        {
          "title": "ironclaw-ai-vision",
          "subtitle": "@shadowlzt",
          "summary": "Ultimate AI Fitness Coach PWA 2026: Iron Mike Workout & Smart Recipe Agent ReflexForge \uD83E\uDDE0⚡ Personal Cognitive Resilience Architect — Offline-First Agentic Mindset Training &...",
          "url": "https://github.com/shadowlzt/ironclaw-ai-vision",
          "category": "HTML",
          "metric": "152 stars",
          "publishedAtUtc": "2026-07-19T02:31:27.0000000Z"
        },
        {
          "title": "omi",
          "subtitle": "@BasedHardware",
          "summary": "AI that sees your screen, listens to your conversations and tells you what to do omi A 2nd brain you trust more than your 1st Omi captures your screen and conversations...",
          "url": "https://github.com/BasedHardware/omi",
          "category": "Dart",
          "metric": "13,025 stars",
          "publishedAtUtc": "2026-07-19T02:31:19.0000000Z"
        }
      ]
    }
  ],
  "items": [
    {
      "title": "v2rayN",
      "subtitle": "@2dust",
      "summary": "A GUI client for Windows, Linux and macOS, support Xray and sing-box and others v2rayN A GUI client for Windows, Linux and macOS.",
      "url": "https://github.com/2dust/v2rayN",
      "category": "C#",
      "metric": "111,702 stars",
      "publishedAtUtc": "2026-07-19T02:20:27.0000000Z"
    },
    {
      "title": "PowerShell",
      "subtitle": "@PowerShell",
      "summary": "PowerShell for every system! ![logo][] PowerShell Welcome to the PowerShell GitHub Community!",
      "url": "https://github.com/PowerShell/PowerShell",
      "category": "C#",
      "metric": "54,423 stars",
      "publishedAtUtc": "2026-07-19T01:50:08.0000000Z"
    },
    {
      "title": "jellyfin",
      "subtitle": "@jellyfin",
      "summary": "The Free Software Media System - Server Backend & API Jellyfin The Free Software Media System -- -- Jellyfin is a Free Software Media System that puts you in control of managing...",
      "url": "https://github.com/jellyfin/jellyfin",
      "category": "C#",
      "metric": "54,417 stars",
      "publishedAtUtc": "2026-07-19T02:10:29.0000000Z"
    },
    {
      "title": "Files",
      "subtitle": "@files-community",
      "summary": "A modern file manager that helps users organize their files and folders. Our mission with Files is to build the best file manager for Windows, and we’re proud to be building it...",
      "url": "https://github.com/files-community/Files",
      "category": "C#",
      "metric": "44,350 stars",
      "publishedAtUtc": "2026-07-19T02:26:16.0000000Z"
    },
    {
      "title": "ShareX",
      "subtitle": "@ShareX",
      "summary": "ShareX is a free and open-source application that enables users to capture or record any area of their screen with a... Screen capture, file sharing and productivity tool For...",
      "url": "https://github.com/ShareX/ShareX",
      "category": "C#",
      "metric": "38,704 stars",
      "publishedAtUtc": "2026-07-19T00:39:02.0000000Z"
    },
    {
      "title": "aspnetcore",
      "subtitle": "@dotnet",
      "summary": "ASP.NET Core is a cross-platform .NET framework for building modern cloud-based web applications on Windows, Mac, or... ASP.NET Core ============ ASP.NET Core is an open-source...",
      "url": "https://github.com/dotnet/aspnetcore",
      "category": "C#",
      "metric": "38,214 stars",
      "publishedAtUtc": "2026-07-18T22:47:07.0000000Z"
    }
  ]
}